pilapse/Product Sans Regular.ttf
pilapse/__main__.py
pilapse/image_saver.py
pilapse/index.html
pilapse/ip_finder.py
pilapse/scheduler.py
pilapse/server.py
pilapse-0.0.13.dist-info/LICENSE
pilapse-0.0.13.dist-info/METADATA
pilapse-0.0.13.dist-info/WHEEL
pilapse-0.0.13.dist-info/entry_points.txt
pilapse-0.0.13.dist-info/top_level.txt
pilapse-0.0.13.dist-info/RECORD
