Metadata-Version: 2.1
Name: pilapse
Version: 0.0.13
Summary: Raspberry Pi time-lapse service
Home-page: https://github.com/yix/pilapse
Author: Alex McGunn
Author-email: mcgunn@oo2.be
License: UNKNOWN
Platform: UNKNOWN
Classifier: Development Status :: 3 - Alpha
Classifier: Programming Language :: Python :: 3
Classifier: License :: OSI Approved :: Apache Software License
Classifier: Operating System :: OS Independent
Requires-Dist: Pillow
